coursetool/__init__.py
coursetool/course.py
coursetool-0.0.3.dist-info/DESCRIPTION.rst
coursetool-0.0.3.dist-info/METADATA
coursetool-0.0.3.dist-info/RECORD
coursetool-0.0.3.dist-info/WHEEL
coursetool-0.0.3.dist-info/entry_points.txt
coursetool-0.0.3.dist-info/metadata.json
coursetool-0.0.3.dist-info/top_level.txt
