Metadata-Version: 2.0
Name: coursetool
Version: 0.0.3
Summary: UNKNOWN
Home-page: UNKNOWN
Author: AnonymousJ
Author-email: UNKNOWN
License: UNKNOWN
Platform: UNKNOWN
Requires-Dist: bs4 (>=0.0.1)
Requires-Dist: lxml (>=3.0.0)
Requires-Dist: requests (>=2.0.0)
